nrfsec/__init__.py
nrfsec/__main__.py
nrfsec/dbg.py
nrfsec/gadget.py
nrfsec/nordic.py
nrfsec/nrfsec.py
nrfsec/utils.py
nrfsec-0.1.3.dist-info/LICENSE
nrfsec-0.1.3.dist-info/METADATA
nrfsec-0.1.3.dist-info/WHEEL
nrfsec-0.1.3.dist-info/dependency_links.txt
nrfsec-0.1.3.dist-info/entry_points.txt
nrfsec-0.1.3.dist-info/top_level.txt
nrfsec-0.1.3.dist-info/RECORD
