Metadata-Version: 2.1
Name: nrfsec
Version: 0.1.3
Summary: An embedded security research tool for unlocking and reading memory from Nordic nRF51 SoCs
Home-page: https://github.com/buildxyz-git/nrfsec
Author: BuildXYZ
Author-email: buildxyz@gmail.com
License: UNKNOWN
Platform: UNKNOWN
Classifier: Programming Language :: Python :: 3
Classifier: License :: OSI Approved :: GNU General Public License v3 (GPLv3)
Classifier: Operating System :: OS Independent
Classifier: Natural Language :: English
Classifier: Intended Audience :: Developers
Classifier: Programming Language :: Python :: 3
Classifier: Topic :: Software Development :: Embedded Systems
Requires-Python: >=3.5
Requires-Dist: pyswd
Requires-Dist: tabulate
Requires-Dist: tqdm
Requires-Dist: argparse
Requires-Dist: coloredlogs
